visualizer_package/__init__.py
visualizer_package/src/__init__.py
visualizer_package/src/cfar_detector.py
visualizer_package/src/evaluation.py
visualizer_package/src/radar_processor.py
visualizer_package/src/utils.py
visualizer_package/src/visualizer.py
visualizer_package-1.2.5.dist-info/LICENSE.TXT
visualizer_package-1.2.5.dist-info/METADATA
visualizer_package-1.2.5.dist-info/WHEEL
visualizer_package-1.2.5.dist-info/top_level.txt
visualizer_package-1.2.5.dist-info/RECORD
