Metadata-Version: 2.1
Name: visualizer-package
Version: 1.2.5
Summary: Python Distribution Utilities
Author: Satyam@UCSD
Author-email: sas043@ucsd.edu
Requires-Python: >=3.0
License-File: LICENSE.TXT
